README.md
setup.py
billing_module/__init__.py
billing_module/billing.py
billing_module/client.py
billing_module/credit_note.py
billing_module/credit_note_footer.py
billing_module/credit_note_header.py
billing_module/invoice.py
billing_module/invoice_detail.py
billing_module/invoice_footer.py
billing_module/invoice_header.py
billing_module/order.py
billing_module/product.py
billing_module/product_detail.py
billing_module/utils.py
billing_module.egg-info/PKG-INFO
billing_module.egg-info/SOURCES.txt
billing_module.egg-info/dependency_links.txt
billing_module.egg-info/top_level.txt
tests/__init__.py
tests/test_billing_process.py
tests/test_multithread_process.py