Metadata-Version: 1.2
Name: billing-module
Version: 0.0.2
Summary: Billing module
Home-page: https://github.com/danilagallo
Author: Danila
Author-email: danilamgallo@gmail.com
License: BSD
Keywords: billing invoice
Platform: UNKNOWN
Requires-Python: >=3.6
